odoo/addons/account_statement_import_online_ponto/README.rst
odoo/addons/account_statement_import_online_ponto/__init__.py
odoo/addons/account_statement_import_online_ponto/__manifest__.py
odoo/addons/account_statement_import_online_ponto/i18n/account_statement_import_online_ponto.pot
odoo/addons/account_statement_import_online_ponto/i18n/ca.po
odoo/addons/account_statement_import_online_ponto/i18n/de.po
odoo/addons/account_statement_import_online_ponto/i18n/es.po
odoo/addons/account_statement_import_online_ponto/i18n/it.po
odoo/addons/account_statement_import_online_ponto/i18n/lv.po
odoo/addons/account_statement_import_online_ponto/i18n/nl.po
odoo/addons/account_statement_import_online_ponto/models/__init__.py
odoo/addons/account_statement_import_online_ponto/models/online_bank_statement_provider_ponto.py
odoo/addons/account_statement_import_online_ponto/models/ponto_interface.py
odoo/addons/account_statement_import_online_ponto/readme/CONFIGURE.md
odoo/addons/account_statement_import_online_ponto/readme/CONTRIBUTORS.md
odoo/addons/account_statement_import_online_ponto/readme/DESCRIPTION.md
odoo/addons/account_statement_import_online_ponto/readme/USAGE.md
odoo/addons/account_statement_import_online_ponto/static/description/icon.png
odoo/addons/account_statement_import_online_ponto/static/description/index.html
odoo/addons/account_statement_import_online_ponto/tests/__init__.py
odoo/addons/account_statement_import_online_ponto/tests/test_account_statement_import_online_ponto.py
odoo/addons/account_statement_import_online_ponto/tests/test_ponto_interface.py
odoo/addons/account_statement_import_online_ponto/views/online_bank_statement_provider.xml
odoo_addon_account_statement_import_online_ponto-18.0.1.0.1.3.dist-info/METADATA
odoo_addon_account_statement_import_online_ponto-18.0.1.0.1.3.dist-info/WHEEL
odoo_addon_account_statement_import_online_ponto-18.0.1.0.1.3.dist-info/top_level.txt
odoo_addon_account_statement_import_online_ponto-18.0.1.0.1.3.dist-info/RECORD
